{
  "_class": "shapePath",
  "booleanOperation": 3,
  "do_objectID": "shapePathsp-1225-0-18",
  "edited": false,
  "exportOptions": {
    "_class": "exportOptions",
    "exportFormats": [
    ],
    "includedLayerIds": [
    ],
    "layerOptions": 0,
    "shouldTrim": false
  },
  "frame": {
    "_class": "rect",
    "constrainProportions": false,
    "height": 90,
    "width": 149,
    "x": 0,
    "y": 0
  },
  "isFlippedHorizontal": false,
  "isFlippedVertical": false,
  "isLocked": false,
  "isVisible": true,
  "layerListExpandedType": 0,
  "name": "Shape sp-1225-0-18",
  "nameIsFixed": false,
  "path": {
    "_class": "path",
    "isClosed": true,
    "pointRadiusBehaviour": 0,
    "points": [
      {
        "_class": "curvePoint",
        "cornerRadius": 0,
        "curveFrom": "{0.73548999999999998, 0.27265899999999998}",
        "curveMode": 2,
        "curveTo": "{0.739232, 0.26993699999999998}",
        "hasCurveFrom": true,
        "hasCurveTo": true,
        "point": "{0.73816000000000004, 0.27174799999999999}"
      },
      {
        "_class": "curvePoint",
        "cornerRadius": 0,
        "curveFrom": "{0.73227799999999998, 0.27084399999999997}",
        "curveMode": 2,
        "curveTo": "{0.73441699999999999, 0.26722200000000002}",
        "hasCurveFrom": true,
        "hasCurveTo": true,
        "point": "{0.73280900000000004, 0.26993699999999998}"
      },
      {
        "_class": "curvePoint",
        "cornerRadius": 0,
        "curveFrom": "{0.73173600000000005, 0.26539600000000002}",
        "curveMode": 2,
        "curveTo": "{0.73067400000000005, 0.26993699999999998}",
        "hasCurveFrom": true,
        "hasCurveTo": true,
        "point": "{0.73120499999999999, 0.26902300000000001}"
      },
      {
        "_class": "curvePoint",
        "cornerRadius": 0,
        "curveFrom": "{0.73816000000000004, 0.25994899999999999}",
        "curveMode": 2,
        "curveTo": "{0.73441699999999999, 0.25994899999999999}",
        "hasCurveFrom": true,
        "hasCurveTo": true,
        "point": "{0.73602100000000004, 0.25723099999999999}"
      },
      {
        "_class": "curvePoint",
        "cornerRadius": 0,
        "curveFrom": "{0.74244399999999999, 0.26902300000000001}",
        "curveMode": 2,
        "curveTo": "{0.73976399999999998, 0.26449400000000001}",
        "hasCurveFrom": true,
        "hasCurveTo": true,
        "point": "{0.741371, 0.26539600000000002}"
      }
    ]
  },
  "resizingConstraint": 63,
  "resizingType": 0,
  "rotation": 0,
  "shouldBreakMaskChain": false
}